sphinx_repo_manager/__init__.py
sphinx_repo_manager/api_reference.py
sphinx_repo_manager/git_helper.py
sphinx_repo_manager/log_styles.py
sphinx_repo_manager/sphinx_repo_manager.py
sphinx_repo_manager-1.0.35.dist-info/LICENSE
sphinx_repo_manager-1.0.35.dist-info/METADATA
sphinx_repo_manager-1.0.35.dist-info/WHEEL
sphinx_repo_manager-1.0.35.dist-info/RECORD
