Metadata-Version: 2.3
Name: sphinx_repo_manager
Version: 1.0.35
Summary: This Sphinx extension by Xsolla Backend [XBE] automates the management of multiple documentation repositories as part of building a larger, unified documentation system. It facilitates multi-threaded cloning and updating of external repositories specified in a YAML manifest file before Sphinx builds.
License: MIT
Author: Xsolla Backend
Author-email: xbe@xsolla.com
Requires-Python: >=3.10
Classifier: Framework :: Sphinx :: Extension
Classifier: Intended Audience :: Developers
Classifier: License :: OSI Approved :: MIT License
Classifier: Operating System :: OS Independent
Classifier: Programming Language :: Python :: 3
Classifier: Programming Language :: Python :: 3.10
Classifier: Programming Language :: Python :: 3.11
Classifier: Programming Language :: Python :: 3.12
Classifier: Programming Language :: Python :: 3.13
Classifier: Topic :: Software Development :: Build Tools
Classifier: Topic :: Software Development :: Documentation
Classifier: Topic :: Software Development :: Version Control
Requires-Dist: PyYAML (>=6.0.2)
Requires-Dist: colorama (>=0.4.6)
Requires-Dist: python-dotenv (>=1.0.1)
Requires-Dist: rich (>=13.9.4)
Requires-Dist: sphinx (>=7.3.7)
Project-URL: Homepage, https://github.com/Unidocs1/sphinx_repo_manager
Project-URL: Issues, https://github.com/Unidocs1/sphinx_repo_manager/issues
